wheel_dep_check/__init__.py
wheel_dep_check/wheel_dep_check.py
wheel_dep_check-0.1.0.dist-info/METADATA
wheel_dep_check-0.1.0.dist-info/WHEEL
wheel_dep_check-0.1.0.dist-info/entry_points.txt
wheel_dep_check-0.1.0.dist-info/top_level.txt
wheel_dep_check-0.1.0.dist-info/RECORD
