Metadata-Version: 2.4
Name: wheel-dep-check
Version: 0.1.0
Summary: Check missing shared library dependencies in Python wheels
Requires-Python: >=3.8
